fast_perceiver/__init__.py
fast_perceiver/adapters.py
fast_perceiver/perceiver.py
fast_perceiver/utils/__init__.py
fast_perceiver/utils/encodings.py
fast_perceiver/utils/training.py
fast_perceiver-0.1.7.dist-info/METADATA
fast_perceiver-0.1.7.dist-info/WHEEL
fast_perceiver-0.1.7.dist-info/RECORD
