Metadata-Version: 2.1
Name: fast-perceiver
Version: 0.1.7
Summary: Fast and memory efficient PyTorch implementation of the Perceiver with FlashAttention.
Author: Kristian Klemon
Author-email: kristian.klemon@gmail.com
Requires-Python: >=3.10,<4.0
Classifier: Programming Language :: Python :: 3
Classifier: Programming Language :: Python :: 3.10
Classifier: Programming Language :: Python :: 3.11
Requires-Dist: einops (>=0.7.0,<0.8.0)
Requires-Dist: torch (>=2.0.1,<3.0.0)
Requires-Dist: torchvision (>=0.15.2,<0.16.0)
